echoss_query/__init__.py
echoss_query/elastic_search.py
echoss_query/mongo_query.py
echoss_query/mysql_query.py
echoss_query-1.0.8.dist-info/METADATA
echoss_query-1.0.8.dist-info/WHEEL
echoss_query-1.0.8.dist-info/top_level.txt
echoss_query-1.0.8.dist-info/RECORD
