Metadata-Version: 2.1
Name: echoss_query
Version: 1.0.8
Summary: echoss AI Bigdata Solution - Query Package
Home-page: 
Author: incheolshin
Author-email: incheolshin@12cm.co.kr
Requires-Python: >3.7
Requires-Dist: pandas>=1.5.3
Requires-Dist: pymongo>=4.3.3
Requires-Dist: PyMySQL>=1.0.2
Requires-Dist: PyYAML>=6.0
Requires-Dist: opensearch-py>=2.2.0
Requires-Dist: echoss-fileformat>=1.1.2
